signal_messenger/__init__.py
signal_messenger/client.py
signal_messenger/exceptions.py
signal_messenger/models.py
signal_messenger/utils.py
signal_messenger/modules/__init__.py
signal_messenger/modules/accounts.py
signal_messenger/modules/attachments.py
signal_messenger/modules/contacts.py
signal_messenger/modules/devices.py
signal_messenger/modules/general.py
signal_messenger/modules/groups.py
signal_messenger/modules/identities.py
signal_messenger/modules/messages.py
signal_messenger/modules/profiles.py
signal_messenger/modules/reactions.py
signal_messenger/modules/receipts.py
signal_messenger/modules/search.py
signal_messenger/modules/stickers.py
signal_messenger_python_api-0.1.0.dist-info/licenses/LICENSE
tests/__init__.py
tests/test_accounts.py
tests/test_attachments.py
tests/test_contacts.py
tests/test_devices.py
tests/test_general.py
tests/test_groups.py
tests/test_identities.py
tests/test_messages.py
tests/test_profiles.py
tests/test_reactions.py
tests/test_receipts.py
tests/test_search.py
tests/test_stickers.py
signal_messenger_python_api-0.1.0.dist-info/METADATA
signal_messenger_python_api-0.1.0.dist-info/WHEEL
signal_messenger_python_api-0.1.0.dist-info/top_level.txt
signal_messenger_python_api-0.1.0.dist-info/RECORD
