Metadata-Version: 2.4
Name: signal-messenger-python-api
Version: 0.1.0
Summary: Asynchronous Python wrapper for the Signal CLI REST API
Home-page: https://github.com/pcko1/signal-messenger-python-api
Author: pcko1
Author-email: hi@pankotsias.com
Classifier: Programming Language :: Python :: 3
Classifier: Programming Language :: Python :: 3.9
Classifier: Programming Language :: Python :: 3.10
Classifier: Programming Language :: Python :: 3.11
Classifier: Programming Language :: Python :: 3.12
Classifier: Programming Language :: Python :: 3.13
Classifier: Programming Language :: Python :: 3.14
Classifier: License :: OSI Approved :: MIT License
Classifier: Operating System :: OS Independent
Classifier: Development Status :: 3 - Alpha
Classifier: Intended Audience :: Developers
Classifier: Topic :: Communications :: Chat
Requires-Python: >=3.9
License-File: LICENSE
Requires-Dist: aiohttp>=3.7.4
Requires-Dist: pydantic>=1.8.2
Provides-Extra: dev
Requires-Dist: pytest>=6.0.0; extra == "dev"
Requires-Dist: pytest-asyncio>=0.14.0; extra == "dev"
Requires-Dist: pytest-cov>=2.10.0; extra == "dev"
Requires-Dist: black>=21.5b2; extra == "dev"
Requires-Dist: isort>=5.9.1; extra == "dev"
Requires-Dist: mypy>=0.812; extra == "dev"
Requires-Dist: flake8>=3.9.2; extra == "dev"
Dynamic: author
Dynamic: author-email
Dynamic: classifier
Dynamic: description
Dynamic: description-content-type
Dynamic: home-page
Dynamic: license-file
Dynamic: provides-extra
Dynamic: requires-dist
Dynamic: requires-python
Dynamic: summary
